darrow_poc/__init__.py
darrow_poc/_version.py
darrow_poc/models/__init__.py
darrow_poc/models/anomaly_detection.py
darrow_poc/models/linear_quantile_regressor.py
darrow_poc/models/poc.py
darrow_poc/models/validation_model.py
darrow_poc-0.1.8.dist-info/LICENSE
darrow_poc-0.1.8.dist-info/METADATA
darrow_poc-0.1.8.dist-info/WHEEL
darrow_poc-0.1.8.dist-info/top_level.txt
darrow_poc-0.1.8.dist-info/RECORD
