Metadata-Version: 2.1
Name: darrow-poc
Version: 0.1.8
Summary: Proof of concept for twinn-ml-interface with model pipeline for predicting water throughput in ruhr river.
License: MIT
Project-URL: homepage, https://github.com/RoyalHaskoningDHV/darrow-poc
Project-URL: issues, https://github.com/RoyalHaskoningDHV/darrow-poc/issues
Project-URL: discussions, https://github.com/RoyalHaskoningDHV/darrow-poc/discussions
Classifier: Programming Language :: Python :: 3
Classifier: License :: OSI Approved :: MIT License
Classifier: Operating System :: OS Independent
Requires-Python: <3.11,>=3.10
License-File: LICENSE
Requires-Dist: annotation-protocol
Requires-Dist: twinn-ml-interface
Requires-Dist: dill
Requires-Dist: geopandas
Requires-Dist: matplotlib
Requires-Dist: pandas
Requires-Dist: python-dotenv
Requires-Dist: sam
Requires-Dist: scikit-learn
Requires-Dist: scipy
Requires-Dist: statsmodels
Requires-Dist: seaborn
Requires-Dist: pytest
Requires-Dist: pyarrow
